{
  "New Minitest spec": {
    "prefix": ["Minitest"],
    "body": [
      "# frozen_string_literal: true",
      "",
      "require \"spec_helper\"",
      "",
      "class $1 < Minitest::Spec",
      "  describe \"$2\" do",
      "    it \"$3\" do",
      "      $0",
      "      assert(true)",
      "    end",
      "  end",
      "end",
      ""
    ],
    "description": "New Minitest class using the spec syntax."
  },
  "New Minitest test": {
    "prefix": ["Minitest"],
    "body": [
      "# frozen_string_literal: true",
      "",
      "require \"test_helper\"",
      "",
      "class $1 < Minitest::Test",
      "  def test_$2",
      "    $0",
      "    assert(true)",
      "  end",
      "end",
      ""
    ],
    "description": "New Minitest class using the test syntax."
  },
  "New Rspec test": {
    "prefix": ["Rspec"],
    "body": [
      "# frozen_string_literal: true",
      "",
      "describe $1 do",
      "  describe \"$2\" do",
      "    it \"$3\" do",
      "      $0",
      "      expect(true).to eq(true)",
      "    end",
      "  end",
      "end",
      ""
    ],
    "description": "New Minitest class using the spec syntax."
  },
  "New class": {
    "prefix": ["class"],
    "body": ["class $1", "  def initialize", "    $0", "  end", "end", ""],
    "description": "New Ruby class."
  },
  "New module": {
    "prefix": ["module"],
    "body": ["module $1", "  def $2", "    $0", "  end", "end", ""],
    "description": "New Ruby module."
  }
}
